databind/__init__.py
databind/binary/__init__.py
databind/binary/_converters.py
databind/binary/_types.py
databind/binary/py.typed
databind/binary/test_binary.py
databind.binary-0.2.1.dist-info/LICENSE.txt
databind.binary-0.2.1.dist-info/METADATA
databind.binary-0.2.1.dist-info/WHEEL
databind.binary-0.2.1.dist-info/top_level.txt
databind.binary-0.2.1.dist-info/RECORD
