Metadata-Version: 2.1
Name: databind.binary
Version: 0.2.1
Summary: Bind object-oriented data models to binary data encoded with the struct module.
Home-page: https://github.com/NiklasRosenstein/python-databind
Author: Niklas Rosenstein
Author-email: rosensteinniklas@gmail.com
License: MIT
Platform: UNKNOWN
Requires-Python: >=3.6.0,<4.0.0
Requires-Dist: databind.core (<1.0.0,>=0.1.0)
